gltf_draco_transcoder/__init__.py
gltf_draco_transcoder/__main__.py
gltf_draco_transcoder/_version.py
gltf_draco_transcoder/libgltf_draco_transcoder.so
gltf_draco_transcoder/libgltf_draco_transcoder.so.0
gltf_draco_transcoder/libgltf_draco_transcoder.so.0.1.0
gltf_draco_transcoder/loader.py
gltf_draco_transcoder/py.typed
gltf_draco_transcoder.libs/libgcc_s-2d945d6c.so.1
gltf_draco_transcoder.libs/libstdc++-85f2cd6d.so.6.0.33
gltf_draco_transcoder-0.2.7.dist-info/METADATA
gltf_draco_transcoder-0.2.7.dist-info/WHEEL
gltf_draco_transcoder-0.2.7.dist-info/RECORD
gltf_draco_transcoder-0.2.7.dist-info/licenses/LICENSE
gltf_draco_transcoder-0.2.7.dist-info/sboms/auditwheel.cdx.json
